bbob_jax/__init__.py
bbob_jax/plotting.py
bbob_jax/_src/__init__.py
bbob_jax/_src/bbob.py
bbob_jax/_src/plotting.py
bbob_jax/_src/registry.py
bbob_jax/_src/tags.py
bbob_jax/_src/utils.py
bbob_jax-1.2.0.dist-info/licenses/LICENSE
bbob_jax-1.2.0.dist-info/METADATA
bbob_jax-1.2.0.dist-info/WHEEL
bbob_jax-1.2.0.dist-info/top_level.txt
bbob_jax-1.2.0.dist-info/RECORD
