Metadata-Version: 2.4
Name: bbob-jax
Version: 1.2.0
Summary: BBOB Benchmark function implemented in JAX
Author-email: "M.P. van der Schelling" <m.p.vanderschelling@tudelft.nl>
License: BSD-3-Clause
Project-URL: repository, https://github.com/bessagroup/bbob-jax
Keywords: jax,bbob,benchmarking,black-box,optimization
Classifier: License :: OSI Approved :: BSD License
Classifier: Development Status :: 3 - Alpha
Classifier: Intended Audience :: Developers
Classifier: Intended Audience :: Information Technology
Classifier: Intended Audience :: Science/Research
Classifier: Natural Language :: English
Classifier: Programming Language :: Python :: 3
Classifier: Topic :: Scientific/Engineering :: Artificial Intelligence
Classifier: Topic :: Scientific/Engineering :: Information Analysis
Classifier: Topic :: Scientific/Engineering :: Mathematics
Requires-Python: >=3.10
License-File: LICENSE
Requires-Dist: jax
Requires-Dist: jaxtyping>=0.3.3
Provides-Extra: dev
Requires-Dist: pre-commit>=4.4.0; extra == "dev"
Requires-Dist: mypy>=1.14.0; extra == "dev"
Provides-Extra: docs
Requires-Dist: mkdocs-gen-files>=0.5.0; extra == "docs"
Requires-Dist: mkdocs-include-exclude-files>=0.1.0; extra == "docs"
Requires-Dist: mkdocs-ipynb>=0.1.1; extra == "docs"
Requires-Dist: mkdocs-material>=9.6.20; extra == "docs"
Requires-Dist: mkdocstrings>=0.30.1; extra == "docs"
Requires-Dist: mkdocstrings-python>=1.18.2; extra == "docs"
Requires-Dist: pymdown-extensions>=10.16.1; extra == "docs"
Provides-Extra: plot
Requires-Dist: matplotlib>=3.10.7; extra == "plot"
Provides-Extra: tests
Requires-Dist: pytest; extra == "tests"
Dynamic: license-file
